mimesis/__init__.py
mimesis/model.py
mimesis/reflect.py
mimesis/thought.py
mimesis/tools.py
mimesis_ai-0.1.dist-info/LICENSE
mimesis_ai-0.1.dist-info/METADATA
mimesis_ai-0.1.dist-info/WHEEL
mimesis_ai-0.1.dist-info/top_level.txt
mimesis_ai-0.1.dist-info/RECORD
