Metadata-Version: 2.1
Name: mimesis-ai
Version: 0.1
Summary: Agents
Home-page: https://www.python.org/sigs/distutils-sig/
Author: Nicolás Rivas
Author-email: Nico <nico@getworkwise.ai>
Project-URL: Homepage, https://github.com/pypa/sampleproject
Project-URL: Bug Tracker, https://github.com/pypa/sampleproject/issues
Classifier: Programming Language :: Python :: 3
Classifier: License :: OSI Approved :: MIT License
Classifier: Operating System :: OS Independent
Requires-Python: >=3.7
License-File: LICENSE
